src/universal_learning/__init__.py
src/universal_learning/solomonoff_comprehensive_config.py
src/universal_learning/solomonoff_core.py
src/universal_learning/solomonoff_research_solutions.py
src/universal_learning/solomonoff_solutions.py
src/universal_learning/utm_program_enumeration_complete.py
src/universal_learning/config/__init__.py
src/universal_learning/config/config_classes.py
src/universal_learning/config/defaults.py
src/universal_learning/config/enums.py
src/universal_learning/core/__init__.py
src/universal_learning/core/algorithmic_probability.py
src/universal_learning/core/kolmogorov_complexity.py
src/universal_learning/core/program_enumeration.py
src/universal_learning/core/solomonoff_induction.py
src/universal_learning/core/universal_prediction.py
src/universal_learning/old_archive/solomonoff_modules/__init__.py
src/universal_learning/old_archive/solomonoff_modules/compression_methods.py
src/universal_learning/old_archive/solomonoff_modules/configuration_methods.py
src/universal_learning/old_archive/solomonoff_modules/pattern_detection.py
src/universal_learning/old_archive/solomonoff_modules/prediction_algorithms.py
src/universal_learning/old_archive/solomonoff_modules/program_generation.py
src/universal_learning/old_archive/solomonoff_modules/program_generation_advanced.py
src/universal_learning/old_archive/solomonoff_modules/program_generation_core.py
src/universal_learning/old_archive/solomonoff_modules/program_generation_original_2356_lines.py
src/universal_learning/old_archive/solomonoff_modules/program_generation_patterns.py
src/universal_learning/old_archive/solomonoff_modules/program_generation_utm.py
src/universal_learning/old_archive/solomonoff_modules/theoretical_analysis.py
src/universal_learning/old_archive/solomonoff_modules/utm_simulation.py
src/universal_learning/utils/__init__.py
src/universal_learning/utils/compression_utils.py
src/universal_learning/utils/performance.py
src/universal_learning/utils/sequence_utils.py
universal_learning-1.3.0.dist-info/METADATA
universal_learning-1.3.0.dist-info/WHEEL
universal_learning-1.3.0.dist-info/licenses/LICENSE
universal_learning-1.3.0.dist-info/RECORD
